py_domaincolor/__init__.py
py_domaincolor/domain_coloring.py
py_domaincolor/plot_complex.py
py_domaincolor/py.typed
py_domaincolor-2.0.0.dist-info/METADATA
py_domaincolor-2.0.0.dist-info/WHEEL
py_domaincolor-2.0.0.dist-info/entry_points.txt
py_domaincolor-2.0.0.dist-info/licenses/LICENSE
py_domaincolor-2.0.0.dist-info/RECORD
