Metadata-Version: 2.4
Name: py-domaincolor
Version: 2.0.0
Summary: Domain coloring visualization for complex-valued functions - a convenience wrapper around cplot and complex-expr-parser
Project-URL: Documentation, https://py-domaincolor.readthedocs.io
Project-URL: Repository, https://github.com/egoughnour/py-domaincolor
Project-URL: Issues, https://github.com/egoughnour/py-domaincolor/issues
Author: Erik Goughnour
License-Expression: MIT
License-File: LICENSE
Keywords: complex-analysis,complex-functions,domain-coloring,mathematics,phase-portrait,visualization
Classifier: Development Status :: 4 - Beta
Classifier: Intended Audience :: Education
Classifier: Intended Audience :: Science/Research
Classifier: License :: OSI Approved :: MIT License
Classifier: Operating System :: OS Independent
Classifier: Programming Language :: Python :: 3
Classifier: Programming Language :: Python :: 3.10
Classifier: Programming Language :: Python :: 3.11
Classifier: Programming Language :: Python :: 3.12
Classifier: Topic :: Scientific/Engineering :: Mathematics
Classifier: Topic :: Scientific/Engineering :: Visualization
Requires-Python: >=3.10
Requires-Dist: complex-expr-parser>=0.1.0
Requires-Dist: cplot>=0.9.0
Requires-Dist: matplotlib>=3.4.0
Requires-Dist: numpy>=1.20.0
Provides-Extra: dev
Requires-Dist: pytest-cov>=4.0.0; extra == 'dev'
Requires-Dist: pytest>=7.0.0; extra == 'dev'
Requires-Dist: sphinx-autodoc-typehints>=1.22.0; extra == 'dev'
Requires-Dist: sphinx-rtd-theme>=1.0.0; extra == 'dev'
Requires-Dist: sphinx>=6.0.0; extra == 'dev'
Provides-Extra: docs
Requires-Dist: sphinx-autodoc-typehints>=1.22.0; extra == 'docs'
Requires-Dist: sphinx-rtd-theme>=1.0.0; extra == 'docs'
Requires-Dist: sphinx>=6.0.0; extra == 'docs'
